biosphere/__init__.py
biosphere/biosphere.cpython-38-x86_64-linux-gnu.so
biosphere-0.4.2.dist-info/METADATA
biosphere-0.4.2.dist-info/WHEEL
biosphere-0.4.2.dist-info/RECORD
biosphere-0.4.2.dist-info/licenses/LICENSE
