Metadata-Version: 2.4
Name: biosphere
Version: 0.4.2
Classifier: License :: OSI Approved :: BSD License
Classifier: Programming Language :: Python
License-File: LICENSE
Summary: Simple, fast random forests
Requires-Python: >=3.7
Project-URL: homepage, https://github.com/mlondschien/biosphere/
